Reg_DI.v
//////////////////////////////////////////////////////////////////////
//
//Reg_DI.v
//
//Este modulo sirve como registro DI
//
//////////////////////////////////////////////////////////////////////

module Reg_DI (
    input wire CLK,
    input wire RST,
    input wire WRITE_EN,
    input wire [1:0] SEL,     // Solo válido 00
    input wire [15:0] IN,
    output reg [15:0] OUT
    );

    reg [15:0] DI;

    always @(posedge CLK or posedge RST) begin
        if (RST) begin
            DI = 16'h0000;
        end else if (WRITE_EN) begin
            DI = IN;
        end
    end

    always @(*) begin
        OUT = DI ;
    end
endmodule

//////////////////////////////////////////////////////////////////////

Reg_SI.v
//////////////////////////////////////////////////////////////////////
//
//Reg_SI.v
//
//Este modulo sirve como registro SI
//
//////////////////////////////////////////////////////////////////////

module Reg_SI (
    input wire CLK,
    input wire RST,
    input wire WRITE_EN,
    input wire [1:0] SEL,     // Solo válido 00
    input wire [15:0] IN,
    output reg [15:0] OUT
    );

    reg [15:0] SI;

    always @(posedge CLK or posedge RST) begin
        if (RST) begin
            SI = 16'h0000;
        end else if (WRITE_EN) begin
            SI = IN;
        end
    end

    always @(*) begin
        OUT =  SI;
    end
endmodule

//////////////////////////////////////////////////////////////////////

Reg_BP.v
//////////////////////////////////////////////////////////////////////
//
//Reg_BP.v
//
//Este modulo sirve como registro BP
//
//////////////////////////////////////////////////////////////////////

module Reg_BP (
    input wire CLK,
    input wire RST,
    input wire WRITE_EN,
    input wire [1:0] SEL,    
    input wire [15:0] IN,
    output reg [15:0] OUT
    );

    reg [15:0] BP;

    always @(posedge CLK or posedge RST) begin
        if (RST) begin
            BP = 16'h0000;
        end
        else if (WRITE_EN) begin
            BP = IN;
        end
    end

    always @(*) begin
        OUT = BP;
    end

endmodule

//////////////////////////////////////////////////////////////////////

Reg_SP.v
//////////////////////////////////////////////////////////////////////
//
//Reg_SP.v
//
//Este modulo sirve como registro SP
//
//////////////////////////////////////////////////////////////////////

module Reg_SP (
    input wire CLK,
    input wire RST,
    input wire WRITE_EN,
    input wire [15:0] IN,
    output reg [15:0] OUT
    );

    reg [15:0] SP;

    always @(posedge CLK or posedge RST) begin
        if (RST) begin
            SP = 16'h0000;  
        end else if (WRITE_EN) begin
            SP = IN;
        end
    end

    always @(*) begin
        OUT = SP;
    end

endmodule

//////////////////////////////////////////////////////////////////////

Reg_DX.v
//////////////////////////////////////////////////////////////////////
//
//Reg_DX.v
//
//Este modulo sirve como registro DX
//
//////////////////////////////////////////////////////////////////////

module Reg_DX (
    input wire CLK,
    input wire RST,
    input wire WRITE_EN,
    input wire [1:0] SEL,     // 00: DX completo, 01: LSB, 10: MSB
    input wire [15:0] IN, 
    output reg [15:0] OUT
    );

    reg [15:0] DX;

    always @(posedge CLK or posedge RST) begin
        if (RST) begin
            DX = 16'b0;
        end else if (WRITE_EN) begin
            case (SEL)
                2'b00,
                2'b11: DX = IN;                        // DX completo
                2'b01: DX[7:0] = IN[7:0];              // LSB
                2'b10: DX[15:8] = IN[15:8];            // MSB
            endcase
        end
    end

    always @(*) begin
        case (SEL)
            2'b00,
            2'b11: OUT = DX;               // DX completo
            2'b01: OUT = {8'b0, DX[7:0]};  // DX (completo también válido)
            2'b10: OUT = {DX[15:8], 8'b0}; // igual que arriba
            default: OUT = 16'b0;
        endcase
    end
endmodule

//////////////////////////////////////////////////////////////////////

Reg_CX.v
//////////////////////////////////////////////////////////////////////
//
//Reg_CX.v
//
//Este modulo sirve como registro CX
//
//////////////////////////////////////////////////////////////////////



module Reg_CX (
    input wire CLK,
    input wire RST,
    input wire WRITE_EN,
    input wire [1:0] SEL,     // 00: CX completo, 01: LSB, 10: MSB
    input wire [15:0] IN, 
    output reg [15:0] OUT
    );

    reg [15:0] CX;

    always @(posedge CLK or posedge RST) begin
        if (RST) begin
            CX = 16'b0;
        end else if (WRITE_EN) begin
            case (SEL)
                2'b00,
                2'b11: CX = IN;                        // CX completo
                2'b01: CX[7:0] = IN[7:0];              // LSB
                2'b10: CX[15:8] = IN[15:8];            // MSB
            endcase
        end
    end

    always @(*) begin
        case (SEL)
            2'b00,
            2'b11: OUT = CX;               // CX completo
            2'b01: OUT = {8'b0, CX[7:0]};  // CX (completo también válido)
            2'b10: OUT = {CX[15:8], 8'b0}; // igual que arriba
            default: OUT = 16'b0;
        endcase
    end
endmodule

//////////////////////////////////////////////////////////////////////

Reg_BX.v
//////////////////////////////////////////////////////////////////////
//
//Reg_BX.v
//
//Este modulo sirve como registro BX
//
//////////////////////////////////////////////////////////////////////

module Reg_BX (
    input wire CLK,
    input wire RST,
    input wire WRITE_EN,
    input wire [1:0] SEL,     // 00: BX completo, 01: LSB, 10: MSB
    input wire [15:0] IN, 
    output reg [15:0] OUT
    );

    reg [15:0] BX;

    always @(posedge CLK or posedge RST) begin
        if (RST) begin
            BX = 16'b0;
        end else if (WRITE_EN) begin
            case (SEL)
                2'b00,
                2'b11: BX = IN;                        // BX completo
                2'b01: BX[7:0] = IN[7:0];              // LSB
                2'b10: BX[15:8] = IN[15:8];            // MSB
            endcase
        end
    end

    always @(*) begin
        case (SEL)
            2'b00,
            2'b11: OUT = BX;               // BX completo
            2'b01: OUT = {8'b0, BX[7:0]};  // BX (completo también válido)
            2'b10: OUT = {BX[15:8], 8'b0}; // igual que arriba
            default: OUT = 16'b0;
        endcase
    end
endmodule

//////////////////////////////////////////////////////////////////////

Reg_AX.v
//////////////////////////////////////////////////////////////////////
//
//Reg_AX.v
//
//Este modulo sirve como registro AX
//
//////////////////////////////////////////////////////////////////////


module Reg_AX (
    input wire CLK,
    input wire RST,
    input wire WRITE_EN,
    input wire [1:0] SEL,   // 00: AX completo, 01: LSB, 10: MSB
    input wire [15:0] IN, 
    output reg [15:0] OUT
    );

    reg [15:0] AX;

    always @(posedge CLK or posedge RST) begin
        if (RST) begin
            AX = 16'b0;
        end 
        else if (WRITE_EN) begin
            case (SEL)
                2'b00,
                2'b11: AX = IN;                        // AX completo
                2'b01: AX[7:0] = IN[7:0];              // LSB
                2'b10: AX[15:8] = IN[15:8];            // MSB
            endcase
        end
    end

    always @(*) begin
        case (SEL)
            2'b00,
            2'b11: OUT = AX;                // AX completo
            2'b01: OUT = {8'b0, AX[7:0]};   // AX (completo también válido)
            2'b10: OUT = {AX[15:8], 8'b0};  // igual que arriba
            default: OUT = 16'b0;
        endcase
    end
endmodule

//////////////////////////////////////////////////////////////////////

Modulo_principal.v
//////////////////////////////////////////////////////////////////////
//
//Modulo_principal.v
//
//Este modulo sirve como modulo principal del 8088
//
//////////////////////////////////////////////////////////////////////

`include "Reg_AX.v"
`include "Reg_BX.v"
`include "Reg_CX.v"
`include "Reg_DX.v"
`include "Reg_SP.v"
`include "Reg_BP.v"
`include "Reg_SI.v"
`include "Reg_DI.v"

module Reg_8088_16_bits (
    input wire CLK,
    input wire RST,
    input wire WRITE_EN,
    input wire [2:0] ADDR,   // Dirección del registro: 000=AX, 001=BX, etc.
    input wire [1:0] SEL,    // Para registros parciales: 00=16 bits, 01=LSB, 10=MSB
    input wire [15:0] IN,
    output wire [15:0] OUT
    );

    // Salidas internas de cada registro
    wire [15:0] AX_OUT, BX_OUT, CX_OUT, DX_OUT;
    wire [15:0] SP_OUT, BP_OUT, SI_OUT, DI_OUT;

    // Instancias de los registros
    Reg_AX u_AX (.CLK(CLK), .RST(RST), .WRITE_EN(WRITE_EN && 
                ADDR == 3'b000), .SEL(SEL), .IN(IN), .OUT(AX_OUT));

    Reg_BX u_BX (.CLK(CLK), .RST(RST), .WRITE_EN(WRITE_EN && 
                ADDR == 3'b001), .SEL(SEL), .IN(IN), .OUT(BX_OUT));

    Reg_CX u_CX (.CLK(CLK), .RST(RST), .WRITE_EN(WRITE_EN && 
                ADDR == 3'b010), .SEL(SEL), .IN(IN), .OUT(CX_OUT));

    Reg_DX u_DX (.CLK(CLK), .RST(RST), .WRITE_EN(WRITE_EN && 
                ADDR == 3'b011), .SEL(SEL), .IN(IN), .OUT(DX_OUT));

    Reg_SP u_SP (.CLK(CLK), .RST(RST), .WRITE_EN(WRITE_EN && 
                ADDR == 3'b100), .IN(IN), .OUT(SP_OUT));

    Reg_BP u_BP (.CLK(CLK), .RST(RST), .WRITE_EN(WRITE_EN && 
                ADDR == 3'b101), .IN(IN), .OUT(BP_OUT));

    Reg_SI u_SI (.CLK(CLK), .RST(RST), .WRITE_EN(WRITE_EN && 
                ADDR == 3'b110), .IN(IN), .OUT(SI_OUT));

    Reg_DI u_DI (.CLK(CLK), .RST(RST), .WRITE_EN(WRITE_EN && 
                ADDR == 3'b111), .IN(IN), .OUT(DI_OUT));

    // Multiplexor de salida
    assign OUT = (ADDR == 3'b000) ? AX_OUT : //0
                 (ADDR == 3'b001) ? BX_OUT : //1
                 (ADDR == 3'b010) ? CX_OUT : //2
                 (ADDR == 3'b011) ? DX_OUT : //3
                 (ADDR == 3'b100) ? SP_OUT : //4
                 (ADDR == 3'b101) ? BP_OUT : //5
                 (ADDR == 3'b110) ? SI_OUT : //6
                 (ADDR == 3'b111) ? DI_OUT : //7
                 16'h0000;

endmodule

//////////////////////////////////////////////////////////////////////

Modulo_principal_tb.sv
//////////////////////////////////////////////////////////////////////
//
//Modulo_principal_tb.sv
//
//Este modulo sirve como testbench del banco de registros del
//procesador Intel 8088
//
//////////////////////////////////////////////////////////////////////

`include "Modulo_principal.v"

module Modulo_principal_tb;

    bit CLK, RST, WRITE_EN;
    bit  [2:0]  ADDR;
    bit  [1:0]  SEL;
    bit  [15:0] IN;
    wire [15:0] OUT;

    //Instancia del modulo principal
    Reg_8088_16_bits DUT (CLK, RST, WRITE_EN, ADDR, SEL, IN, OUT);

    bit [15:0] registros_esperados [7:0];
    bit [15:0] valor_esperado;

    //TESTER
        //Declaratoria inicial de reloj
        initial begin
            CLK = 0;
            forever 
                #10 CLK = ~CLK; 
        end

        initial begin
            $dumpfile("Wavetb.vcd"); // Nombre del archivo VCD
            $dumpvars(0, Modulo_principal_tb);   // 'testbench' debe ser el nombre del módulo de prueba
        end

        //Escoger registro de manera aleatoria
        function  bit [2:0] reg_random();

            bit [2:0] selec_reg;
            selec_reg = $urandom_range(0, 7); // Valores válidos: 000 (AX) a 111 (DI)
            return selec_reg;

        endfunction : reg_random

        //Genera un dato random
        function bit [15:0] dato_random();

            bit [15:0] dato;
            dato = $urandom;
            return dato;

        endfunction : dato_random

        //Escoge si usar parte alta o baja del reg
        function bit [1:0] sel_random();

            bit [1:0] sel_HL;
            sel_HL = $urandom;
            return sel_HL;

        endfunction : sel_random


        //Cuerpo del tester
        initial begin : tester

            RST = 1;
            @(posedge CLK);
            @(posedge CLK);         //Esperar 1 ciclo
            RST = 0;
            @(posedge CLK);
            @(posedge CLK);

            repeat (1000) begin
            
                RST = 0;
                SEL = sel_random();
                ADDR = reg_random();
                IN = dato_random();
                
                WRITE_EN = 1;

                @(posedge CLK);
                WRITE_EN = 0;
                @(posedge CLK);

            end

            #20 $finish;

        end : tester

    // SCOREBOARD
        always @(negedge WRITE_EN) begin

                // Calcular el valor esperado
                if (ADDR <= 3) begin

                    case (SEL)
                        2'b01: valor_esperado = {8'h00, IN[7:0]};        // LSB escrita, MSB se borra
                        2'b10: valor_esperado = {IN[15:8], 8'h00};       // MSB escrita, LSB se borra
                        2'b00,
                        2'b11: valor_esperado = IN;                      // Escritura completa
                        default: valor_esperado = 16'h0000;              // Default defensivo
                    endcase
                end else begin

                    valor_esperado = IN;

                end
                
                // Actualizar el scoreboard
                registros_esperados[ADDR] = valor_esperado;

                // Verificación (compara OUT del ciclo anterior)
                #1
                if (OUT !== valor_esperado)
                    $error("[SB] Error en Registro %0d: Esperado = %h, Leído = %h", ADDR, valor_esperado, OUT);
                else
                    $display("[SB] Correcto Registro %0d <- %h, OUT = %h, H_L <- %b", ADDR, IN, OUT, SEL);  
        end

endmodule

//////////////////////////////////////////////////////////////////////

Wavetb.vcd
$date
	Sun Apr 06 20:35:45 2025
$end
$version
	Icarus Verilog
$end
$timescale
	1s
$end
$scope module Modulo_principal_tb $end
$var wire 16 ! OUT [15:0] $end
$var reg 3 " ADDR [2:0] $end
$var reg 1 # CLK $end
$var reg 16 $ IN [15:0] $end
$var reg 1 % RST $end
$var reg 2 & SEL [1:0] $end
$var reg 1 ' WRITE_EN $end
$var reg 16 ( valor_esperado [15:0] $end
$scope function dato_random $end
$var reg 16 ) dato [15:0] $end
$upscope $end
$scope function reg_random $end
$var reg 3 * selec_reg [2:0] $end
$upscope $end
$scope function sel_random $end
$var reg 2 + sel_HL [1:0] $end
$upscope $end
$scope module DUT $end
$var wire 3 , ADDR [2:0] $end
$var wire 1 # CLK $end
$var wire 16 - IN [15:0] $end
$var wire 1 % RST $end
$var wire 2 . SEL [1:0] $end
$var wire 1 ' WRITE_EN $end
$var wire 16 / SP_OUT [15:0] $end
$var wire 16 0 SI_OUT [15:0] $end
$var wire 16 1 OUT [15:0] $end
$var wire 16 2 DX_OUT [15:0] $end
$var wire 16 3 DI_OUT [15:0] $end
$var wire 16 4 CX_OUT [15:0] $end
$var wire 16 5 BX_OUT [15:0] $end
$var wire 16 6 BP_OUT [15:0] $end
$var wire 16 7 AX_OUT [15:0] $end
$scope module u_AX $end
$var wire 1 # CLK $end
$var wire 16 8 IN [15:0] $end
$var wire 1 % RST $end
$var wire 2 9 SEL [1:0] $end
$var wire 1 : WRITE_EN $end
$var reg 16 ; AX [15:0] $end
$var reg 16 < OUT [15:0] $end
$upscope $end
$scope module u_BP $end
$var wire 1 # CLK $end
$var wire 16 = IN [15:0] $end
$var wire 1 % RST $end
$var wire 2 > SEL [1:0] $end
$var wire 1 ? WRITE_EN $end
$var reg 16 @ BP [15:0] $end
$var reg 16 A OUT [15:0] $end
$upscope $end
$scope module u_BX $end
$var wire 1 # CLK $end
$var wire 16 B IN [15:0] $end
$var wire 1 % RST $end
$var wire 2 C SEL [1:0] $end
$var wire 1 D WRITE_EN $end
$var reg 16 E BX [15:0] $end
$var reg 16 F OUT [15:0] $end
$upscope $end
$scope module u_CX $end
$var wire 1 # CLK $end
$var wire 16 G IN [15:0] $end
$var wire 1 % RST $end
$var wire 2 H SEL [1:0] $end
$var wire 1 I WRITE_EN $end
$var reg 16 J CX [15:0] $end
$var reg 16 K OUT [15:0] $end
$upscope $end
$scope module u_DI $end
$var wire 1 # CLK $end
$var wire 16 L IN [15:0] $end
$var wire 1 % RST $end
$var wire 2 M SEL [1:0] $end
$var wire 1 N WRITE_EN $end
$var reg 16 O DI [15:0] $end
$var reg 16 P OUT [15:0] $end
$upscope $end
$scope module u_DX $end
$var wire 1 # CLK $end
$var wire 16 Q IN [15:0] $end
$var wire 1 % RST $end
$var wire 2 R SEL [1:0] $end
$var wire 1 S WRITE_EN $end
$var reg 16 T DX [15:0] $end
$var reg 16 U OUT [15:0] $end
$upscope $end
$scope module u_SI $end
$var wire 1 # CLK $end
$var wire 16 V IN [15:0] $end
$var wire 1 % RST $end
$var wire 2 W SEL [1:0] $end
$var wire 1 X WRITE_EN $end
$var reg 16 Y OUT [15:0] $end
$var reg 16 Z SI [15:0] $end
$upscope $end
$scope module u_SP $end
$var wire 1 # CLK $end
$var wire 16 [ IN [15:0] $end
$var wire 1 % RST $end
$var wire 1 \ WRITE_EN $end
$var reg 16 ] OUT [15:0] $end
$var reg 16 ^ SP [15:0] $end
$upscope $end
$upscope $end
$scope begin tester $end
$upscope $end
$upscope $end
$enddefinitions $end
$comment Show the parameter values. $end
$dumpall
$end
#0
$dumpvars
b0 ^
b0 ]
0\
b0 [
b0 Z
b0 Y
0X
bz W
b0 V
b0 U
b0 T
0S
b0 R
b0 Q
b0 P
b0 O
0N
bz M
b0 L
b0 K
b0 J
0I
b0 H
b0 G
b0 F
b0 E
0D
b0 C
b0 B
b0 A
b0 @
0?
bz >
b0 =
b0 <
b0 ;
0:
b0 9
b0 8
b0 7
b0 6
b0 5
b0 4
b0 3
b0 2
b0 1
b0 0
b0 /
b0 .
b0 -
b0 ,
b0 +
b0 *
b0 )
b0 (
0'
b0 &
1%
b0 $
0#
b0 "
b0 !
$end
#10
1#
#20
0#
#30
0%
1#
#40
0#
#50
1#
#60
0#
#70
1I
1'
b1101011000001001 $
b1101011000001001 -
b1101011000001001 8
b1101011000001001 =
b1101011000001001 B
b1101011000001001 G
b1101011000001001 L
b1101011000001001 Q
b1101011000001001 V
b1101011000001001 [
b1101011000001001 )
b10 "
b10 ,
b10 *
1#
#80
0#
#90
b1101011000001001 !
b1101011000001001 1
b1101011000001001 4
b1101011000001001 K
0I
b1101011000001001 (
b1101011000001001 J
0'
1#
#100
0#
#110
b0 !
b0 1
1\
1'
b1001100110001101 $
b1001100110001101 -
b1001100110001101 8
b1001100110001101 =
b1001100110001101 B
b1001100110001101 G
b1001100110001101 L
b1001100110001101 Q
b1001100110001101 V
b1001100110001101 [
b1001100110001101 )
b100 "
b100 ,
b100 *
b11 &
b11 .
b11 9
b11 C
b11 H
b11 R
b11 +
1#
#120
0#
#130
b1001100110001101 !
b1001100110001101 1
b1001100110001101 /
b1001100110001101 ]
0\
b1001100110001101 (
b1001100110001101 ^
0'
1#
#140
0#
#150
1:
b0 !
b0 1
b1001 4
b1001 K
1'
b1110001100000001 $
b1110001100000001 -
b1110001100000001 8
b1110001100000001 =
b1110001100000001 B
b1110001100000001 G
b1110001100000001 L
b1110001100000001 Q
b1110001100000001 V
b1110001100000001 [
b1110001100000001 )
b0 "
b0 ,
b0 *
b1 &
b1 .
b1 9
b1 C
b1 H
b1 R
b1 +
1#
#160
0#
#170
b1 !
b1 1
b1 7
b1 <
0:
b1 (
b1 ;
0'
1#
#180
0#
#190
1?
b0 !
b0 1
1'
b1100110100111101 $
b1100110100111101 -
b1100110100111101 8
b1100110100111101 =
b1100110100111101 B
b1100110100111101 G
b1100110100111101 L
b1100110100111101 Q
b1100110100111101 V
b1100110100111101 [
b1100110100111101 )
b101 "
b101 ,
b101 *
1#
#200
0#
#210
b1100110100111101 !
b1100110100111101 1
b1100110100111101 6
b1100110100111101 A
0?
b1100110100111101 (
b1100110100111101 @
0'
1#
#220
0#
#230
b0 !
b0 1
1X
1'
b1110100111111001 $
b1110100111111001 -
b1110100111111001 8
b1110100111111001 =
b1110100111111001 B
b1110100111111001 G
b1110100111111001 L
b1110100111111001 Q
b1110100111111001 V
b1110100111111001 [
b1110100111111001 )
b110 "
b110 ,
b110 *
1#
#240
0#
#250
b1110100111111001 !
b1110100111111001 1
b1110100111111001 0
b1110100111111001 Y
0X
b1110100111111001 (
b1110100111111001 Z
0'
1#
#260
0#
#270
b0 !
b0 1
1S
b0 7
b0 <
b1101011000000000 4
b1101011000000000 K
1'
b1101001010101010 $
b1101001010101010 -
b1101001010101010 8
b1101001010101010 =
b1101001010101010 B
b1101001010101010 G
b1101001010101010 L
b1101001010101010 Q
b1101001010101010 V
b1101001010101010 [
b1101001010101010 )
b11 "
b11 ,
b11 *
b10 &
b10 .
b10 9
b10 C
b10 H
b10 R
b10 +
1#
#280
0#
#290
b1101001000000000 !
b1101001000000000 1
b1101001000000000 2
b1101001000000000 U
0S
b1101001000000000 (
b1101001000000000 T
0'
1#
#300
0#
#310
b0 !
b0 1
1D
b1 7
b1 <
b1001 4
b1001 K
b0 2
b0 U
1'
b1101011000010010 $
b1101011000010010 -
b1101011000010010 8
b1101011000010010 =
b1101011000010010 B
b1101011000010010 G
b1101011000010010 L
b1101011000010010 Q
b1101011000010010 V
b1101011000010010 [
b1101011000010010 )
b1 "
b1 ,
b1 *
b1 &
b1 .
b1 9
b1 C
b1 H
b1 R
b1 +
1#
#320
0#
#330
b10010 !
b10010 1
b10010 5
b10010 F
0D
b10010 (
b10010 E
0'
1#
#340
0#
#350
b0 !
b0 1
1N
b1101011000001001 4
b1101011000001001 K
b1101001000000000 2
b1101001000000000 U
1'
b1001011011001110 $
b1001011011001110 -
b1001011011001110 8
b1001011011001110 =
b1001011011001110 B
b1001011011001110 G
b1001011011001110 L
b1001011011001110 Q
b1001011011001110 V
b1001011011001110 [
b1001011011001110 )
b111 "
b111 ,
b111 *
b11 &
b11 .
b11 9
b11 C
b11 H
b11 R
b11 +
1#
#360
0#
#370
b1001011011001110 !
b1001011011001110 1
b1001011011001110 3
b1001011011001110 P
0N
b1001011011001110 (
b1001011011001110 O
0'
1#
#380
0#
#390
b1101001000000000 !
b1101001000000000 1
1S
1'
b100100101011100 $
b100100101011100 -
b100100101011100 8
b100100101011100 =
b100100101011100 B
b100100101011100 G
b100100101011100 L
b100100101011100 Q
b100100101011100 V
b100100101011100 [
b100100101011100 )
b11 "
b11 ,
b11 *
b0 &
b0 .
b0 9
b0 C
b0 H
b0 R
b0 +
1#
#400
0#
#410
b100100101011100 !
b100100101011100 1
b100100101011100 2
b100100101011100 U
0S
b100100101011100 (
b100100101011100 T
0'
1#
#420
0#
#430
1:
b1 !
b1 1
b1001 4
b1001 K
b1011100 2
b1011100 U
1'
b10011001100101 $
b10011001100101 -
b10011001100101 8
b10011001100101 =
b10011001100101 B
b10011001100101 G
b10011001100101 L
b10011001100101 Q
b10011001100101 V
b10011001100101 [
b10011001100101 )
b0 "
b0 ,
b0 *
b1 &
b1 .
b1 9
b1 C
b1 H
b1 R
b1 +
1#
#440
0#
#450
b1100101 !
b1100101 1
b1100101 7
b1100101 <
0:
b1100101 (
b1100101 ;
0'
1#
#460
0#
#470
1\
b1001100110001101 !
b1001100110001101 1
b1101011000001001 4
b1101011000001001 K
b100100101011100 2
b100100101011100 U
1'
b10001010000000 $
b10001010000000 -
b10001010000000 8
b10001010000000 =
b10001010000000 B
b10001010000000 G
b10001010000000 L
b10001010000000 Q
b10001010000000 V
b10001010000000 [
b10001010000000 )
b100 "
b100 ,
b100 *
b11 &
b11 .
b11 9
b11 C
b11 H
b11 R
b11 +
1#
#480
0#
#490
b10001010000000 !
b10001010000000 1
b10001010000000 /
b10001010000000 ]
0\
b10001010000000 (
b10001010000000 ^
0'
1#
#500
0#
#510
b1110100111111001 !
b1110100111111001 1
1X
1'
b1100110010011101 $
b1100110010011101 -
b1100110010011101 8
b1100110010011101 =
b1100110010011101 B
b1100110010011101 G
b1100110010011101 L
b1100110010011101 Q
b1100110010011101 V
b1100110010011101 [
b1100110010011101 )
b110 "
b110 ,
b110 *
b0 &
b0 .
b0 9
b0 C
b0 H
b0 R
b0 +
1#
#520
0#
#530
b1100110010011101 !
b1100110010011101 1
b1100110010011101 0
b1100110010011101 Y
0X
b1100110010011101 (
b1100110010011101 Z
0'
1#
#540
0#
#550
1:
b0 !
b0 1
b0 7
b0 <
b0 5
b0 F
b1101011000000000 4
b1101011000000000 K
b100100100000000 2
b100100100000000 U
1'
b11100000001101 $
b11100000001101 -
b11100000001101 8
b11100000001101 =
b11100000001101 B
b11100000001101 G
b11100000001101 L
b11100000001101 Q
b11100000001101 V
b11100000001101 [
b11100000001101 )
b0 "
b0 ,
b0 *
b10 &
b10 .
b10 9
b10 C
b10 H
b10 R
b10 +
1#
#560
0#
#570
b11100000000000 !
b11100000000000 1
b11100000000000 7
b11100000000000 <
0:
b11100000000000 (
b11100001100101 ;
0'
1#
#580
0#
#590
1?
b1100110100111101 !
b1100110100111101 1
b11100001100101 7
b11100001100101 <
b10010 5
b10010 F
b1101011000001001 4
b1101011000001001 K
b100100101011100 2
b100100101011100 U
1'
b10101011010101 $
b10101011010101 -
b10101011010101 8
b10101011010101 =
b10101011010101 B
b10101011010101 G
b10101011010101 L
b10101011010101 Q
b10101011010101 V
b10101011010101 [
b10101011010101 )
b101 "
b101 ,
b101 *
b11 &
b11 .
b11 9
b11 C
b11 H
b11 R
b11 +
1#
#600
0#
#610
b10101011010101 !
b10101011010101 1
b10101011010101 6
b10101011010101 A
0?
b10101011010101 (
b10101011010101 @
0'
1#
#620
0#
#630
b1101011000000000 !
b1101011000000000 1
1I
b11100000000000 7
b11100000000000 <
b0 5
b0 F
b1101011000000000 4
b1101011000000000 K
b100100100000000 2
b100100100000000 U
1'
b1110100100011101 $
b1110100100011101 -
b1110100100011101 8
b1110100100011101 =
b1110100100011101 B
b1110100100011101 G
b1110100100011101 L
b1110100100011101 Q
b1110100100011101 V
b1110100100011101 [
b1110100100011101 )
b10 "
b10 ,
b10 *
b10 &
b10 .
b10 9
b10 C
b10 H
b10 R
b10 +
1#
#640
0#
#650
b1110100100000000 !
b1110100100000000 1
b1110100100000000 4
b1110100100000000 K
0I
b1110100100000000 (
b1110100100001001 J
0'
1#
#660
0#
#670
b10001010000000 !
b10001010000000 1
1\
b11100001100101 7
b11100001100101 <
b10010 5
b10010 F
b1110100100001001 4
b1110100100001001 K
b100100101011100 2
b100100101011100 U
1'
b110010100001010 $
b110010100001010 -
b110010100001010 8
b110010100001010 =
b110010100001010 B
b110010100001010 G
b110010100001010 L
b110010100001010 Q
b110010100001010 V
b110010100001010 [
b110010100001010 )
b100 "
b100 ,
b100 *
b11 &
b11 .
b11 9
b11 C
b11 H
b11 R
b11 +
1#
#680
0#
#690
b110010100001010 !
b110010100001010 1
b110010100001010 /
b110010100001010 ]
0\
b110010100001010 (
b110010100001010 ^
0'
1#
#700
0#
#710
1:
b11100000000000 !
b11100000000000 1
b11100000000000 7
b11100000000000 <
b0 5
b0 F
b1110100100000000 4
b1110100100000000 K
b100100100000000 2
b100100100000000 U
1'
b1011110111110010 $
b1011110111110010 -
b1011110111110010 8
b1011110111110010 =
b1011110111110010 B
b1011110111110010 G
b1011110111110010 L
b1011110111110010 Q
b1011110111110010 V
b1011110111110010 [
b1011110111110010 )
b0 "
b0 ,
b0 *
b10 &
b10 .
b10 9
b10 C
b10 H
b10 R
b10 +
1#
#720
0#
#730
b1011110100000000 !
b1011110100000000 1
b1011110100000000 7
b1011110100000000 <
0:
b1011110100000000 (
b1011110101100101 ;
0'
1#
#740
0#
#750
1?
b10101011010101 !
b10101011010101 1
1'
b11010011011000 $
b11010011011000 -
b11010011011000 8
b11010011011000 =
b11010011011000 B
b11010011011000 G
b11010011011000 L
b11010011011000 Q
b11010011011000 V
b11010011011000 [
b11010011011000 )
b101 "
b101 ,
b101 *
1#
#760
0#
#770
b11010011011000 !
b11010011011000 1
b11010011011000 6
b11010011011000 A
0?
b11010011011000 (
b11010011011000 @
0'
1#
#780
0#
#790
b1110100100001001 !
b1110100100001001 1
1I
b1011110101100101 7
b1011110101100101 <
b10010 5
b10010 F
b1110100100001001 4
b1110100100001001 K
b100100101011100 2
b100100101011100 U
1'
b110111101011 $
b110111101011 -
b110111101011 8
b110111101011 =
b110111101011 B
b110111101011 G
b110111101011 L
b110111101011 Q
b110111101011 V
b110111101011 [
b110111101011 )
b10 "
b10 ,
b10 *
b0 &
b0 .
b0 9
b0 C
b0 H
b0 R
b0 +
1#
#800
0#
#810
b110111101011 !
b110111101011 1
b110111101011 4
b110111101011 K
0I
b110111101011 (
b110111101011 J
0'
1#
#820
0#
#830
b1001011011001110 !
b1001011011001110 1
1N
b1011110100000000 7
b1011110100000000 <
b0 5
b0 F
b110100000000 4
b110100000000 K
b100100100000000 2
b100100100000000 U
1'
b1001110101110 $
b1001110101110 -
b1001110101110 8
b1001110101110 =
b1001110101110 B
b1001110101110 G
b1001110101110 L
b1001110101110 Q
b1001110101110 V
b1001110101110 [
b1001110101110 )
b111 "
b111 ,
b111 *
b10 &
b10 .
b10 9
b10 C
b10 H
b10 R
b10 +
1#
#840
0#
#850
b1001110101110 !
b1001110101110 1
b1001110101110 3
b1001110101110 P
0N
b1001110101110 (
b1001110101110 O
0'
1#
#860
0#
#870
b110010100001010 !
b110010100001010 1
1\
b1011110101100101 7
b1011110101100101 <
b10010 5
b10010 F
b110111101011 4
b110111101011 K
b100100101011100 2
b100100101011100 U
1'
b1001101000001011 $
b1001101000001011 -
b1001101000001011 8
b1001101000001011 =
b1001101000001011 B
b1001101000001011 G
b1001101000001011 L
b1001101000001011 Q
b1001101000001011 V
b1001101000001011 [
b1001101000001011 )
b100 "
b100 ,
b100 *
b0 &
b0 .
b0 9
b0 C
b0 H
b0 R
b0 +
1#
#880
0#
#890
b1001101000001011 !
b1001101000001011 1
b1001101000001011 /
b1001101000001011 ]
0\
b1001101000001011 (
b1001101000001011 ^
0'
1#
#900
0#
#910
b1100110010011101 !
b1100110010011101 1
1X
b1100101 7
b1100101 <
b11101011 4
b11101011 K
b1011100 2
b1011100 U
1'
b101010101001111 $
b101010101001111 -
b101010101001111 8
b101010101001111 =
b101010101001111 B
b101010101001111 G
b101010101001111 L
b101010101001111 Q
b101010101001111 V
b101010101001111 [
b101010101001111 )
b110 "
b110 ,
b110 *
b1 &
b1 .
b1 9
b1 C
b1 H
b1 R
b1 +
1#
#920
0#
#930
b101010101001111 !
b101010101001111 1
b101010101001111 0
b101010101001111 Y
0X
b101010101001111 (
b101010101001111 Z
0'
1#
#940
0#
#950
b1001101000001011 !
b1001101000001011 1
1\
b1011110101100101 7
b1011110101100101 <
b110111101011 4
b110111101011 K
b100100101011100 2
b100100101011100 U
1'
b11001001111110 $
b11001001111110 -
b11001001111110 8
b11001001111110 =
b11001001111110 B
b11001001111110 G
b11001001111110 L
b11001001111110 Q
b11001001111110 V
b11001001111110 [
b11001001111110 )
b100 "
b100 ,
b100 *
b11 &
b11 .
b11 9
b11 C
b11 H
b11 R
b11 +
1#
#960
0#
#970
b11001001111110 !
b11001001111110 1
b11001001111110 /
b11001001111110 ]
0\
b11001001111110 (
b11001001111110 ^
0'
1#
#980
0#
